azureml/__init__.py
azureml/contrib/__init__.py
azureml/contrib/datadrift/__init__.py
azureml_contrib_datadrift-1.0.85.dist-info/DESCRIPTION.rst
azureml_contrib_datadrift-1.0.85.dist-info/LICENSE.txt
azureml_contrib_datadrift-1.0.85.dist-info/METADATA
azureml_contrib_datadrift-1.0.85.dist-info/RECORD
azureml_contrib_datadrift-1.0.85.dist-info/WHEEL
azureml_contrib_datadrift-1.0.85.dist-info/metadata.json
azureml_contrib_datadrift-1.0.85.dist-info/top_level.txt
