Metadata-Version: 2.0
Name: azureml-contrib-datadrift
Version: 1.0.85
Summary: Azure Machine Learning datadrift
Home-page: https://docs.microsoft.com/en-us/azure/machine-learning/service/
Author: Microsoft Corp
License: Proprietary https://aka.ms/azureml-preview-sdk-license 
Platform: UNKNOWN
Provides-Extra: databricks
Requires-Dist: azureml-core (==1.0.85.*)
Requires-Dist: azureml-datadrift (==1.0.85.*)
Requires-Dist: azureml-telemetry (==1.0.85.*)
Requires-Dist: azureml-pipeline-core (==1.0.85.*)
Requires-Dist: azureml-pipeline-steps (==1.0.85.*)
Requires-Dist: msrest (>=0.5.1)
Requires-Dist: numpy
Requires-Dist: pandas
Requires-Dist: scipy (>=1.0.0)
Requires-Dist: scikit-learn
Requires-Dist: lightgbm
Requires-Dist: jsonpickle
Requires-Dist: pyspark
Requires-Dist: azureml-dataprep[pandas,fuse] (<1.2.0a,>=1.1.37a)
Requires-Dist: matplotlib (>=3.0.2)
Provides-Extra: databricks
Requires-Dist: pyOpenSSL (==16.0.0); extra == 'databricks'
Requires-Dist: cryptography (==1.5); extra == 'databricks'
Requires-Dist: ipython (==2.2.0); extra == 'databricks'
Requires-Dist: numpy (<=1.16.2,>=1.11.0); extra == 'databricks'
Requires-Dist: pandas (<=0.23.4,>=0.21.0); extra == 'databricks'
Requires-Dist: scipy (<=1.1.0,>=1.0.0); extra == 'databricks'
Requires-Dist: tornado (==5.1.1); extra == 'databricks'
